setup.py
kleenex/__init__.py
kleenex/config.py
kleenex/db.py
kleenex/diff.py
kleenex/plugin.py
kleenex/tracer.py
nose_kleenex.egg-info/PKG-INFO
nose_kleenex.egg-info/SOURCES.txt
nose_kleenex.egg-info/dependency_links.txt
nose_kleenex.egg-info/entry_points.txt
nose_kleenex.egg-info/not-zip-safe
nose_kleenex.egg-info/requires.txt
nose_kleenex.egg-info/top_level.txt
tests/config/__init__.py
tests/config/tests.py
tests/db/__init__.py
tests/db/tests.py